example_pkg/__init__.py
scarecrow_data-0.0.4.dist-info/LICENSE
scarecrow_data-0.0.4.dist-info/METADATA
scarecrow_data-0.0.4.dist-info/WHEEL
scarecrow_data-0.0.4.dist-info/top_level.txt
scarecrow_data-0.0.4.dist-info/RECORD
