Metadata-Version: 2.1
Name: scarecrow-data
Version: 0.0.4
Summary: Scarecrow offers low code web development for data science.
Home-page: https://github.com/mdghayman/Scarecrow
Author: Michael Hayman
Author-email: mdghayman@gmail.com
License: UNKNOWN
Platform: UNKNOWN
Classifier: Programming Language :: Python :: 3
Classifier: License :: OSI Approved :: MIT License
Classifier: Operating System :: OS Independent
Requires-Python: >=3.6
